zxvcv/__init__.py
zxvcv/util_cli/__init__.py
zxvcv/util_cli/__main__.py
zxvcv/util_cli/datatypes.py
zxvcv/util_cli/vscreens.py
zxvcv.util_cli-0.2.6.dist-info/LICENSE
zxvcv.util_cli-0.2.6.dist-info/METADATA
zxvcv.util_cli-0.2.6.dist-info/WHEEL
zxvcv.util_cli-0.2.6.dist-info/top_level.txt
zxvcv.util_cli-0.2.6.dist-info/zip-safe
zxvcv.util_cli-0.2.6.dist-info/RECORD
